MCIntAna/__init__.py
MCIntAna/modulo.py
MC_Int/__init__.py
MC_Int/modulo.py
MCIntAna-0.1.2.dist-info/METADATA
MCIntAna-0.1.2.dist-info/WHEEL
MCIntAna-0.1.2.dist-info/top_level.txt
MCIntAna-0.1.2.dist-info/RECORD
